tracking_util/__init__.py
tracking_util/io/__init__.py
tracking_util/io/fileio.py
tracking_util/io/seqio.py
tracking_util/utils/__init__.py
tracking_util/utils/gtutils.py
tracking_util/utils/visutils.py
tracking_util-0.1.1.dist-info/LICENSE
tracking_util-0.1.1.dist-info/METADATA
tracking_util-0.1.1.dist-info/WHEEL
tracking_util-0.1.1.dist-info/top_level.txt
tracking_util-0.1.1.dist-info/RECORD
